[{"title": "TEST DATA 1", "start": "November 10, 2018 6:00 PM", "end": "November 10, 2018 7:00 PM"}, {"title": "TEST DATA 2", "start": "November 8, 2018 12:56 PM", "end": "November 8, 2018 1:30 PM"}, {"title": "IDENTICAL DATA", "start": "November 6, 2018 5:00 PM", "end": "November 6, 2018 10:00 PM"}, {"title": "IDENTICAL DATA", "start": "November 6, 2018 5:00 PM", "end": "November 6, 2018 10:00 PM"}, {"title": "TEST DATA 5", "start": "November 7, 2018 12:00 PM", "end": "November 7, 2018 2:30 PM"}, {"title": "DATA 6 with same date", "start": "November 7, 2018 12:00 PM", "end": "November 7, 2018 2:30 PM"}]
